konfoo/__init__.py
konfoo/categories.py
konfoo/core.py
konfoo/enums.py
konfoo/exceptions.py
konfoo/fields.py
konfoo/globals.py
konfoo/options.py
konfoo/pointers.py
konfoo/providers.py
konfoo/utils.py
KonFoo-3.0.0.dist-info/LICENSE
KonFoo-3.0.0.dist-info/METADATA
KonFoo-3.0.0.dist-info/WHEEL
KonFoo-3.0.0.dist-info/top_level.txt
KonFoo-3.0.0.dist-info/RECORD
