Metadata-Version: 2.1
Name: KonFoo
Version: 3.0.0
Summary: A declarative byte stream mapping engine.
Home-page: https://github.com/JoeVirtual/KonFoo/
Download-URL: https://github.com/JoeVirtual/KonFoo/zipball/master#egg=konfoo-dev
Author: Jochen Gerhaeusser
Author-email: jochen_privat@gmx.de
License: BSD-3-Clause
Project-URL: Issue Tracker, https://github.com/JoeVirtual/KonFoo/issues/
Project-URL: Documentation, https://konfoo.readthedocs.io
Project-URL: Source Code, https://github.com/JoeVirtual/KonFoo
Keywords: binary data,deserialize,serialize,parse,decode,encode,unpack,pack
Platform: any
Classifier: Development Status :: 5 - Production/Stable
Classifier: Environment :: Console
Classifier: Environment :: Web Environment
Classifier: Intended Audience :: Developers
Classifier: License :: OSI Approved :: BSD License
Classifier: Natural Language :: English
Classifier: Operating System :: OS Independent
Classifier: Programming Language :: Python
Classifier: Programming Language :: Python :: 3 :: Only
Classifier: Programming Language :: Python :: 3.9
Classifier: Programming Language :: Python :: 3.10
Classifier: Programming Language :: Python :: 3.11
Classifier: Topic :: Software Development
Classifier: Topic :: Software Development :: Embedded Systems
Classifier: Topic :: Software Development :: Testing
Classifier: Topic :: Scientific/Engineering :: Interface Engine/Protocol Translator
Classifier: Topic :: Scientific/Engineering :: Visualization
Requires-Python: >=3.9
License-File: LICENSE
